setup.py
aim_ui/VERSION
aim_ui/__init__.py
aim_ui/build/96a8239122f181f7ed19.worker.js
aim_ui/build/96a8239122f181f7ed19.worker.js.LICENSE.txt
aim_ui/build/96a8239122f181f7ed19.worker.js.gz
aim_ui/build/96a8239122f181f7ed19.worker.js.map
aim_ui/build/asset-manifest.json
aim_ui/build/favicon.ico
aim_ui/build/index-template.html
aim_ui/build/index.html
aim_ui/build/index.html.gz
aim_ui/build/manifest.json
aim_ui/build/robots.txt
aim_ui/build/assets/icomoon/icomoonIcons.css
aim_ui/build/assets/icomoon/icomoonIcons.css.gz
aim_ui/build/assets/icomoon/selection.json
aim_ui/build/assets/icomoon/fonts/icomoon.eot
aim_ui/build/assets/icomoon/fonts/icomoon.svg
aim_ui/build/assets/icomoon/fonts/icomoon.ttf
aim_ui/build/assets/icomoon/fonts/icomoon.woff
aim_ui/build/assets/inconsolata/inconsolata.css
aim_ui/build/assets/inconsolata/inconsolata.css.gz
aim_ui/build/assets/inconsolata/fonts/Inconsolata.ttf
aim_ui/build/assets/inter/inter.css
aim_ui/build/assets/inter/inter.css.gz
aim_ui/build/assets/inter/fonts/Inter.ttf
aim_ui/build/static/css/AudiosVisualizer.css
aim_ui/build/static/css/AudiosVisualizer.css.gz
aim_ui/build/static/css/AudiosVisualizer.css.map
aim_ui/build/static/css/DistributionsVisualizer.css
aim_ui/build/static/css/DistributionsVisualizer.css.gz
aim_ui/build/static/css/DistributionsVisualizer.css.map
aim_ui/build/static/css/ExperimentOverviewTab.css
aim_ui/build/static/css/ExperimentOverviewTab.css.gz
aim_ui/build/static/css/ExperimentOverviewTab.css.map
aim_ui/build/static/css/ImagesVisualizer.css
aim_ui/build/static/css/ImagesVisualizer.css.gz
aim_ui/build/static/css/ImagesVisualizer.css.map
aim_ui/build/static/css/PlotlyVisualizer.css
aim_ui/build/static/css/PlotlyVisualizer.css.gz
aim_ui/build/static/css/PlotlyVisualizer.css.map
aim_ui/build/static/css/RunDetailMetricsAndSystemTab.css
aim_ui/build/static/css/RunDetailMetricsAndSystemTab.css.gz
aim_ui/build/static/css/RunDetailMetricsAndSystemTab.css.map
aim_ui/build/static/css/RunDetailNotesTab.css
aim_ui_custom.egg-info/PKG-INFO
aim_ui_custom.egg-info/SOURCES.txt
aim_ui_custom.egg-info/dependency_links.txt
aim_ui_custom.egg-info/top_level.txt