Metadata-Version: 2.1
Name: aim-ui-custom
Version: 3.15.2.post10
Summary: Aim UI
